MANIFEST.in
README.rst
setup.py
aliyun_python_sdk_release_test.egg-info/PKG-INFO
aliyun_python_sdk_release_test.egg-info/SOURCES.txt
aliyun_python_sdk_release_test.egg-info/dependency_links.txt
aliyun_python_sdk_release_test.egg-info/requires.txt
aliyun_python_sdk_release_test.egg-info/top_level.txt
aliyunsdkecs/__init__.py
aliyunsdkecs/request/__init__.py
aliyunsdkecs/request/v20140526/ActivateRouterInterfaceRequest.py
aliyunsdkecs/request/v20140526/AddBandwidthPackageIpsRequest.py
aliyunsdkecs/request/v20140526/AddDiskRequest.py
aliyunsdkecs/request/v20140526/AddTagsRequest.py
aliyunsdkecs/request/v20140526/AllocateEipAddressRequest.py
aliyunsdkecs/request/v20140526/AllocatePublicIpAddressRequest.py
aliyunsdkecs/request/v20140526/ApplyAutoSnapshotPolicyRequest.py
aliyunsdkecs/request/v20140526/AssociateEipAddressRequest.py
aliyunsdkecs/request/v20140526/AssociateHaVipRequest.py
aliyunsdkecs/request/v20140526/AttachDiskRequest.py
aliyunsdkecs/request/v20140526/AttachInstanceRamRoleRequest.py
aliyunsdkecs/request/v20140526/AttachKeyPairRequest.py
aliyunsdkecs/request/v20140526/AttachVolumeRequest.py
aliyunsdkecs/request/v20140526/AuthorizeSecurityGroupEgressRequest.py
aliyunsdkecs/request/v20140526/AuthorizeSecurityGroupRequest.py
aliyunsdkecs/request/v20140526/CancelAutoSnapshotPolicyRequest.py
aliyunsdkecs/request/v20140526/CancelCopyImageRequest.py
aliyunsdkecs/request/v20140526/CancelPhysicalConnectionRequest.py
aliyunsdkecs/request/v20140526/CancelTaskRequest.py
aliyunsdkecs/request/v20140526/CheckAutoSnapshotPolicyRequest.py
aliyunsdkecs/request/v20140526/CheckDiskEnableAutoSnapshotValidationRequest.py
aliyunsdkecs/request/v20140526/ConnectRouterInterfaceRequest.py
aliyunsdkecs/request/v20140526/CopyImageRequest.py
aliyunsdkecs/request/v20140526/CreateAutoSnapshotPolicyRequest.py
aliyunsdkecs/request/v20140526/CreateDeploymentSetRequest.py
aliyunsdkecs/request/v20140526/CreateDiskRequest.py
aliyunsdkecs/request/v20140526/CreateForwardEntryRequest.py
aliyunsdkecs/request/v20140526/CreateHaVipRequest.py
aliyunsdkecs/request/v20140526/CreateImageRequest.py
aliyunsdkecs/request/v20140526/CreateInstanceRequest.py
aliyunsdkecs/request/v20140526/CreateKeyPairRequest.py
aliyunsdkecs/request/v20140526/CreateNatGatewayRequest.py
