Metadata-Version: 1.0
Name: aliyun-python-sdk-release-test
Version: 2.2.9
Summary: A release test module for Aliyun SDK, please don't use it
Home-page: http://develop.aliyun.com/sdk/python
Author: Aliyun
Author-email: aliyun-developers-efficiency@list.alibaba-inc.com
License: Apache
Platform: any
